{
  "$schema": "../gen/schemas/desktop-schema.json",
  "identifier": "default",
  "description": "Downlink application default capabilities",
  "windows": [
    "main",
    "splashscreen"
  ],
  "permissions": [
    "core:default",
    "core:event:default",
    "core:event:allow-emit",
    "core:event:allow-listen",
    "updater:default",
    "process:default",
    "clipboard-manager:default",
    "notification:default",
    "core:window:default",
    "core:window:allow-start-dragging",
    "clipboard-manager:allow-read-text",
    "clipboard-manager:allow-write-text",
    "core:window:allow-show",
    "core:window:allow-close",
    "core:window:allow-set-decorations",
    "core:window:allow-set-shadow",
    "core:window:allow-set-background-color",
    "core:window:allow-get-all-windows"
  ]
}